{"rows":[{"Instructions":"instructions"},{"TrialNumber":"1","A1":"","B1":"Screwdriver,blocked","C1":"","D1":"LargeRedSock","A2":"blocked","B2":"Egg","C2":"","D2":"blocked","A3":"","B3":"","C3":"Spatula,blocked","D3":"Cards","A4":"Baby, blocked","B4":"Wallet","C4":"","D4":"Pen","Answer":"Egg","CorrectAnswer":"B2","WrongAnswer":"","CorrectPlacement":"C2","Instruction":"Egg - right","Picture":"P1","Soundfile wav":"P1V1.wav","Soundfile":"P1V1","Set":"","Block type":"","Trial type":"","Condition":"","Position":"","Test":""},{"TrialNumber":"2","A1":"","B1":"Screwdriver,blocked","C1":"","D1":"LargeRedSock","A2":"blocked","B2":"Egg","C2":"","D2":"blocked","A3":"","B3":"","C3":"Spatula,blocked","D3":"Cards","A4":"Baby, blocked","B4":"Wallet","C4":"","D4":"Pen","Answer":"LargeRedSock","CorrectAnswer":"D1","WrongAnswer":"","CorrectPlacement":"D2","Instruction":"Sock - down","Picture":"P1","Soundfile wav":"P1V2.wav","Soundfile":"P1V2","Set":"","Block type":"","Trial type":"","Condition":"","Position":"","Test":""},{"TrialNumber":"3","A1":"","B1":"Screwdriver,blocked","C1":"","D1":"LargeRedSock","A2":"blocked","B2":"Egg","C2":"","D2":"blocked","A3":"","B3":"","C3":"Spatula,blocked","D3":"Cards","A4":"Baby, blocked","B4":"Wallet","C4":"","D4":"Pen","Answer":"Wallet","CorrectAnswer":"B4","WrongAnswer":"","CorrectPlacement":"C4","Instruction":"Wallet - right","Picture":"P1","Soundfile wav":"P1V3.wav","Soundfile":"P1V3","Set":"","Block type":"","Trial type":"","Condition":"","Position":"","Test":""},{"Instructions":"letsgo"}],"columns":["TrialNumber","A1","B1","C1","D1","A2","B2","C2","D2","A3","B3","C3","D3","A4","B4","C4","D4","Answer","CorrectAnswer","WrongAnswer","CorrectPlacement","Instruction","Picture","Soundfile wav","Soundfile","Set","Block type","Trial type","Condition","Position","Test","Instructions"]}